isloth_text_processing_service_python_interface/__init__.py
isloth_text_processing_service_python_interface/dtos/ImageProcessorResponse.py
isloth_text_processing_service_python_interface/dtos/ObjectProcessorResponse.py
isloth_text_processing_service_python_interface/dtos/Result.py
isloth_text_processing_service_python_interface/dtos/__init__.py
isloth_text_processing_service_python_interface/dtos/image/ImageObjectInput.py
isloth_text_processing_service_python_interface/dtos/image/__init__.py
isloth_text_processing_service_python_interface/services/ObjectProcessor.py
isloth_text_processing_service_python_interface/services/__init__.py
isloth_text_processing_service_python_interface/services/interfaces/IObjectProcessor.py
isloth_text_processing_service_python_interface/services/interfaces/__init__.py
isloth_text_processing_service_python_interface/utilities/__init__.py
isloth_text_processing_service_python_interface/utilities/helpers/WebClient.py
isloth_text_processing_service_python_interface/utilities/helpers/__init__.py
isloth_text_processing_service_python_interface-0.12.0.dist-info/licenses/LICENSE
isloth_text_processing_service_python_interface-0.12.0.dist-info/METADATA
isloth_text_processing_service_python_interface-0.12.0.dist-info/WHEEL
isloth_text_processing_service_python_interface-0.12.0.dist-info/top_level.txt
isloth_text_processing_service_python_interface-0.12.0.dist-info/RECORD
