Metadata-Version: 2.4
Name: isloth-text-processing-service-python-interface
Version: 0.12.0
Summary: Shared Python library for internal microservices
Author-email: Omid Eghlidos <omid.eghlidos@islothco.com>
License: MIT
Requires-Python: >=3.8
License-File: LICENSE
Dynamic: license-file
